ECHO_modules/DataSet.py
ECHO_modules/DataSetResults.py
ECHO_modules/__init__.py
ECHO_modules/correct_counties.py
ECHO_modules/data_set_presets.py
ECHO_modules/geographies.py
ECHO_modules/get_data.py
ECHO_modules/make_data_sets.py
ECHO_modules/rsei_utilities.py
ECHO_modules/utilities.py
echo_modules-0.2.1.dist-info/licenses/LICENSE
echo_modules-0.2.1.dist-info/WHEEL
echo_modules-0.2.1.dist-info/METADATA
echo_modules-0.2.1.dist-info/RECORD
