Metadata-Version: 2.4
Name: ECHO_modules
Version: 0.2.1
Summary: Python package for analyzing US Environmental Protection Agency datasets including Enforcement and Compliance History Online (ECHO), Risk Screening Environmental Indicators (RSEI), and EJSCREEN
Author-email: Steve Hansen <steven.e.hansen@gmail.com>, Eric Nost <enost@uoguelph.ca>, Sung-Gheel Jang <sunggheel.jang@stonybrook.edu>, Yemoe Aung <enost@uoguelph.ca>, Kelsey Breseman <ye.m.aung@stonybrook.edu>, EDGI <contact@envirodatagov.org>
Classifier: Programming Language :: Python :: 3
Classifier: License :: OSI Approved :: GNU General Public License v3 (GPLv3)
Classifier: Operating System :: OS Independent
License-File: LICENSE
Requires-Dist: delta-spark==3.3.0
Requires-Dist: deltalake==0.16.4
Requires-Dist: folium>=0.14.0
Requires-Dist: geopandas>=0.9.0
Requires-Dist: ipyleaflet==0.19.2
Requires-Dist: ipython>=7.29.0
Requires-Dist: ipywidgets>=7.6.5
Requires-Dist: matplotlib>=3.4.3
Requires-Dist: numpy==2.0.2
Requires-Dist: pandas>=1.3.4
Requires-Dist: pyspark>=3.5.4
Requires-Dist: requests>=2.31.0
Requires-Dist: seaborn>=0.11.2
Requires-Dist: tqdm
Project-URL: Home, https://github.com/edgi-govdata-archiving/ECHO_modules/
Project-URL: Issues, https://github.com/edgi-govdata-archiving/ECHO_modules/issues
